teko/__init__.py
teko/cli/__init__.py
teko/cli/cs_command.py
teko/cli/jira_command.py
teko/cli/main.py
teko/cli/oas_command.py
teko/helpers/__init__.py
teko/helpers/clog.py
teko/helpers/exceptions.py
teko/helpers/file_io.py
teko/models/__init__.py
teko/models/jira_export_test/__init__.py
teko/models/jira_export_test/storage.py
teko/models/jira_export_test/test_case.py
teko/models/jira_export_test/test_cycle.py
teko/models/jira_export_test/test_step.py
teko/models/jira_tool/__init__.py
teko/models/jira_tool/jira_testcase.py
teko/services/__init__.py
teko/services/jira/__init__.py
teko/services/jira/jira_service.py
teko/services/jira_export_test/__init__.py
teko/services/jira_export_test/test_case_service.py
teko/services/jira_export_test/test_cycle_service.py
teko/services/oas/__init__.py
teko/services/oas/oas_service.py
teko/services/oas/compare/__init__.py
teko/services/oas/compare/specification_diff.py
teko/services/oas/parse/__init__.py
teko/services/oas/parse/openapi3/__init__.py
teko/services/oas/parse/openapi3/__main__.py
teko/services/oas/parse/openapi3/components.py
teko/services/oas/parse/openapi3/errors.py
teko/services/oas/parse/openapi3/example.py
teko/services/oas/parse/openapi3/general.py
teko/services/oas/parse/openapi3/info.py
teko/services/oas/parse/openapi3/object_base.py
teko/services/oas/parse/openapi3/openapi.py
teko/services/oas/parse/openapi3/paths.py
teko/services/oas/parse/openapi3/schemas.py
teko/services/oas/parse/openapi3/security.py
teko/services/oas/parse/openapi3/servers.py
teko/services/oas/parse/openapi3/tag.py
teko/templates/cycle.json
teko/templates/cycle.yaml
teko/templates/testcases.json
teko/templates/testcases.yaml
teko/templates/testcases_with_cycle_bundle.json
teko/templates/testcases_with_cycle_bundle.yaml
teko/test/__init__.py
teko/test/test_create_test_from_docstring.py
teko/utils/__init__.py
teko/utils/jira_export_test/__init__.py
teko/utils/jira_export_test/wraper.py
teko_cli-0.12.4.dist-info/METADATA
teko_cli-0.12.4.dist-info/WHEEL
teko_cli-0.12.4.dist-info/entry_points.txt
teko_cli-0.12.4.dist-info/top_level.txt
teko_cli-0.12.4.dist-info/RECORD
