Metadata-Version: 2.1
Name: teko-cli
Version: 0.12.4
Summary: Teko CLI tools
Home-page: https://git.teko.vn/vnpay-marketing-portal/teko-tools
Download-URL: https://pypi.org/project/teko/
Author: Thuc Nguyen
Author-email: thuc.nc@teko.vn
License: MIT
Keywords: Teko,Teko CLI tools
Requires-Dist: requests
Requires-Dist: jinja2
Requires-Dist: tabulate
Requires-Dist: typer
Requires-Dist: colorama
Requires-Dist: dataclasses-json
Requires-Dist: ruamel.yaml
Requires-Dist: python-dotenv
Requires-Dist: bs4
Requires-Dist: pyaml (==21.10.1)
